{
  "team_number": "254",
  "bumper_color": "RED",
  "video_source": "/var/folders/z1/67ld6bcd32ndh86q77h_rhj40000gn/T/scout_8q61_tch/Einstein 3 - FIRST Championship - FIRST Robotics Competition.mp4",
  "scouted_at": "2026-05-11T23:13:19.841172",
  "frames_tracked": 210,
  "tracking_lost": 924,
  "pixel_distance": 1638.4,
  "events": [
    {
      "frame": 215,
      "t": 3.58,
      "event": "Locked \u2192 track #1"
    },
    {
      "frame": 362,
      "t": 6.03,
      "event": "Locked \u2192 track #7"
    },
    {
      "frame": 743,
      "t": 12.38,
      "event": "Locked \u2192 track #30"
    },
    {
      "frame": 1135,
      "t": 18.92,
      "event": "Locked \u2192 track #52"
    }
  ],
  "tracking_data": [
    {
      "frame": 216,
      "t": 3.6,
      "cx": 349,
      "cy": 607,
      "w": 78,
      "h": 29
    },
    {
      "frame": 217,
      "t": 3.62,
      "cx": 349,
      "cy": 607,
      "w": 78,
      "h": 29
    },
    {
      "frame": 218,
      "t": 3.63,
      "cx": 349,
      "cy": 607,
      "w": 78,
      "h": 29
    },
    {
      "frame": 219,
      "t": 3.65,
      "cx": 349,
      "cy": 607,
      "w": 78,
      "h": 29
    },
    {
      "frame": 220,
      "t": 3.67,
      "cx": 349,
      "cy": 607,
      "w": 78,
      "h": 29
    },
    {
      "frame": 221,
      "t": 3.68,
      "cx": 349,
      "cy": 607,
      "w": 78,
      "h": 29
    },
    {
      "frame": 222,
      "t": 3.7,
      "cx": 349,
      "cy": 607,
      "w": 78,
      "h": 29
    },
    {
      "frame": 223,
      "t": 3.72,
      "cx": 349,
      "cy": 607,
      "w": 78,
      "h": 29
    },
    {
      "frame": 224,
      "t": 3.73,
      "cx": 349,
      "cy": 607,
      "w": 78,
      "h": 29
    },
    {
      "frame": 225,
      "t": 3.75,
      "cx": 349,
      "cy": 607,
      "w": 78,
      "h": 29
    },
    {
      "frame": 226,
      "t": 3.77,
      "cx": 349,
      "cy": 607,
      "w": 78,
      "h": 29
    },
    {
      "frame": 227,
      "t": 3.78,
      "cx": 349,
      "cy": 607,
      "w": 78,
      "h": 29
    },
    {
      "frame": 228,
      "t": 3.8,
      "cx": 349,
      "cy": 607,
      "w": 78,
      "h": 29
    },
    {
      "frame": 229,
      "t": 3.82,
      "cx": 349,
      "cy": 607,
      "w": 78,
      "h": 29
    },
    {
      "frame": 230,
      "t": 3.83,
      "cx": 349,
      "cy": 607,
      "w": 78,
      "h": 29
    },
    {
      "frame": 231,
      "t": 3.85,
      "cx": 349,
      "cy": 607,
      "w": 78,
      "h": 29
    },
    {
      "frame": 232,
      "t": 3.87,
      "cx": 349,
      "cy": 607,
      "w": 78,
      "h": 29
    },
    {
      "frame": 233,
      "t": 3.88,
      "cx": 349,
      "cy": 607,
      "w": 78,
      "h": 29
    },
    {
      "frame": 234,
      "t": 3.9,
      "cx": 348,
      "cy": 607,
      "w": 79,
      "h": 29
    },
    {
      "frame": 235,
      "t": 3.92,
      "cx": 348,
      "cy": 607,
      "w": 79,
      "h": 29
    },
    {
      "frame": 236,
      "t": 3.93,
      "cx": 348,
      "cy": 607,
      "w": 79,
      "h": 29
    },
    {
      "frame": 237,
      "t": 3.95,
      "cx": 348,
      "cy": 607,
      "w": 79,
      "h": 29
    },
    {
      "frame": 238,
      "t": 3.97,
      "cx": 348,
      "cy": 607,
      "w": 79,
      "h": 29
    },
    {
      "frame": 239,
      "t": 3.98,
      "cx": 349,
      "cy": 607,
      "w": 80,
      "h": 29
    },
    {
      "frame": 240,
      "t": 4.0,
      "cx": 349,
      "cy": 607,
      "w": 80,
      "h": 29
    },
    {
      "frame": 241,
      "t": 4.02,
      "cx": 349,
      "cy": 607,
      "w": 80,
      "h": 29
    },
    {
      "frame": 242,
      "t": 4.03,
      "cx": 349,
      "cy": 607,
      "w": 80,
      "h": 29
    },
    {
      "frame": 243,
      "t": 4.05,
      "cx": 349,
      "cy": 607,
      "w": 80,
      "h": 29
    },
    {
      "frame": 244,
      "t": 4.07,
      "cx": 349,
      "cy": 607,
      "w": 80,
      "h": 29
    },
    {
      "frame": 245,
      "t": 4.08,
      "cx": 349,
      "cy": 607,
      "w": 80,
      "h": 29
    },
    {
      "frame": 246,
      "t": 4.1,
      "cx": 349,
      "cy": 607,
      "w": 80,
      "h": 29
    },
    {
      "frame": 247,
      "t": 4.12,
      "cx": 349,
      "cy": 607,
      "w": 80,
      "h": 29
    },
    {
      "frame": 248,
      "t": 4.13,
      "cx": 349,
      "cy": 607,
      "w": 80,
      "h": 29
    },
    {
      "frame": 249,
      "t": 4.15,
      "cx": 349,
      "cy": 607,
      "w": 80,
      "h": 29
    },
    {
      "frame": 250,
      "t": 4.17,
      "cx": 349,
      "cy": 607,
      "w": 80,
      "h": 29
    },
    {
      "frame": 251,
      "t": 4.18,
      "cx": 349,
      "cy": 607,
      "w": 80,
      "h": 29
    },
    {
      "frame": 252,
      "t": 4.2,
      "cx": 349,
      "cy": 607,
      "w": 80,
      "h": 29
    },
    {
      "frame": 253,
      "t": 4.22,
      "cx": 349,
      "cy": 607,
      "w": 80,
      "h": 29
    },
    {
      "frame": 254,
      "t": 4.23,
      "cx": 349,
      "cy": 607,
      "w": 80,
      "h": 29
    },
    {
      "frame": 255,
      "t": 4.25,
      "cx": 349,
      "cy": 607,
      "w": 80,
      "h": 29
    },
    {
      "frame": 256,
      "t": 4.27,
      "cx": 349,
      "cy": 607,
      "w": 80,
      "h": 29
    },
    {
      "frame": 257,
      "t": 4.28,
      "cx": 349,
      "cy": 607,
      "w": 80,
      "h": 29
    },
    {
      "frame": 258,
      "t": 4.3,
      "cx": 349,
      "cy": 607,
      "w": 80,
      "h": 29
    },
    {
      "frame": 259,
      "t": 4.32,
      "cx": 349,
      "cy": 607,
      "w": 80,
      "h": 29
    },
    {
      "frame": 260,
      "t": 4.33,
      "cx": 349,
      "cy": 607,
      "w": 80,
      "h": 29
    },
    {
      "frame": 261,
      "t": 4.35,
      "cx": 349,
      "cy": 607,
      "w": 80,
      "h": 29
    },
    {
      "frame": 262,
      "t": 4.37,
      "cx": 349,
      "cy": 607,
      "w": 80,
      "h": 29
    },
    {
      "frame": 263,
      "t": 4.38,
      "cx": 349,
      "cy": 607,
      "w": 80,
      "h": 29
    },
    {
      "frame": 264,
      "t": 4.4,
      "cx": 349,
      "cy": 607,
      "w": 80,
      "h": 29
    },
    {
      "frame": 265,
      "t": 4.42,
      "cx": 349,
      "cy": 607,
      "w": 80,
      "h": 29
    },
    {
      "frame": 266,
      "t": 4.43,
      "cx": 349,
      "cy": 607,
      "w": 80,
      "h": 29
    },
    {
      "frame": 267,
      "t": 4.45,
      "cx": 349,
      "cy": 607,
      "w": 80,
      "h": 29
    },
    {
      "frame": 268,
      "t": 4.47,
      "cx": 348,
      "cy": 607,
      "w": 79,
      "h": 29
    },
    {
      "frame": 269,
      "t": 4.48,
      "cx": 348,
      "cy": 607,
      "w": 79,
      "h": 29
    },
    {
      "frame": 270,
      "t": 4.5,
      "cx": 348,
      "cy": 607,
      "w": 79,
      "h": 29
    },
    {
      "frame": 271,
      "t": 4.52,
      "cx": 348,
      "cy": 607,
      "w": 79,
      "h": 29
    },
    {
      "frame": 272,
      "t": 4.53,
      "cx": 348,
      "cy": 607,
      "w": 79,
      "h": 29
    },
    {
      "frame": 273,
      "t": 4.55,
      "cx": 349,
      "cy": 607,
      "w": 78,
      "h": 29
    },
    {
      "frame": 274,
      "t": 4.57,
      "cx": 349,
      "cy": 607,
      "w": 78,
      "h": 29
    },
    {
      "frame": 275,
      "t": 4.58,
      "cx": 349,
      "cy": 607,
      "w": 78,
      "h": 29
    },
    {
      "frame": 276,
      "t": 4.6,
      "cx": 349,
      "cy": 607,
      "w": 78,
      "h": 29
    },
    {
      "frame": 277,
      "t": 4.62,
      "cx": 349,
      "cy": 607,
      "w": 78,
      "h": 29
    },
    {
      "frame": 278,
      "t": 4.63,
      "cx": 348,
      "cy": 607,
      "w": 79,
      "h": 29
    },
    {
      "frame": 279,
      "t": 4.65,
      "cx": 349,
      "cy": 607,
      "w": 80,
      "h": 29
    },
    {
      "frame": 280,
      "t": 4.67,
      "cx": 349,
      "cy": 607,
      "w": 78,
      "h": 29
    },
    {
      "frame": 281,
      "t": 4.68,
      "cx": 349,
      "cy": 607,
      "w": 79,
      "h": 29
    },
    {
      "frame": 282,
      "t": 4.7,
      "cx": 349,
      "cy": 607,
      "w": 79,
      "h": 29
    },
    {
      "frame": 283,
      "t": 4.72,
      "cx": 349,
      "cy": 607,
      "w": 79,
      "h": 29
    },
    {
      "frame": 284,
      "t": 4.73,
      "cx": 349,
      "cy": 607,
      "w": 79,
      "h": 29
    },
    {
      "frame": 285,
      "t": 4.75,
      "cx": 349,
      "cy": 607,
      "w": 79,
      "h": 29
    },
    {
      "frame": 286,
      "t": 4.77,
      "cx": 349,
      "cy": 607,
      "w": 79,
      "h": 29
    },
    {
      "frame": 287,
      "t": 4.78,
      "cx": 349,
      "cy": 607,
      "w": 79,
      "h": 29
    },
    {
      "frame": 288,
      "t": 4.8,
      "cx": 349,
      "cy": 607,
      "w": 79,
      "h": 29
    },
    {
      "frame": 289,
      "t": 4.82,
      "cx": 349,
      "cy": 607,
      "w": 79,
      "h": 29
    },
    {
      "frame": 290,
      "t": 4.83,
      "cx": 349,
      "cy": 607,
      "w": 79,
      "h": 29
    },
    {
      "frame": 291,
      "t": 4.85,
      "cx": 349,
      "cy": 607,
      "w": 79,
      "h": 29
    },
    {
      "frame": 292,
      "t": 4.87,
      "cx": 349,
      "cy": 607,
      "w": 78,
      "h": 29
    },
    {
      "frame": 293,
      "t": 4.88,
      "cx": 349,
      "cy": 607,
      "w": 78,
      "h": 29
    },
    {
      "frame": 294,
      "t": 4.9,
      "cx": 349,
      "cy": 607,
      "w": 78,
      "h": 29
    },
    {
      "frame": 295,
      "t": 4.92,
      "cx": 349,
      "cy": 607,
      "w": 78,
      "h": 29
    },
    {
      "frame": 296,
      "t": 4.93,
      "cx": 349,
      "cy": 607,
      "w": 78,
      "h": 29
    },
    {
      "frame": 297,
      "t": 4.95,
      "cx": 349,
      "cy": 607,
      "w": 78,
      "h": 29
    },
    {
      "frame": 298,
      "t": 4.97,
      "cx": 349,
      "cy": 607,
      "w": 78,
      "h": 29
    },
    {
      "frame": 299,
      "t": 4.98,
      "cx": 349,
      "cy": 607,
      "w": 79,
      "h": 29
    },
    {
      "frame": 300,
      "t": 5.0,
      "cx": 349,
      "cy": 607,
      "w": 79,
      "h": 29
    },
    {
      "frame": 301,
      "t": 5.02,
      "cx": 349,
      "cy": 607,
      "w": 79,
      "h": 29
    },
    {
      "frame": 302,
      "t": 5.03,
      "cx": 349,
      "cy": 607,
      "w": 78,
      "h": 29
    },
    {
      "frame": 303,
      "t": 5.05,
      "cx": 349,
      "cy": 607,
      "w": 78,
      "h": 29
    },
    {
      "frame": 304,
      "t": 5.07,
      "cx": 349,
      "cy": 607,
      "w": 78,
      "h": 29
    },
    {
      "frame": 305,
      "t": 5.08,
      "cx": 351,
      "cy": 607,
      "w": 82,
      "h": 29
    },
    {
      "frame": 306,
      "t": 5.1,
      "cx": 350,
      "cy": 607,
      "w": 81,
      "h": 29
    },
    {
      "frame": 307,
      "t": 5.12,
      "cx": 350,
      "cy": 607,
      "w": 81,
      "h": 29
    },
    {
      "frame": 308,
      "t": 5.13,
      "cx": 351,
      "cy": 607,
      "w": 82,
      "h": 29
    },
    {
      "frame": 309,
      "t": 5.15,
      "cx": 351,
      "cy": 607,
      "w": 82,
      "h": 29
    },
    {
      "frame": 310,
      "t": 5.17,
      "cx": 351,
      "cy": 607,
      "w": 82,
      "h": 29
    },
    {
      "frame": 311,
      "t": 5.18,
      "cx": 351,
      "cy": 607,
      "w": 82,
      "h": 29
    },
    {
      "frame": 312,
      "t": 5.2,
      "cx": 350,
      "cy": 607,
      "w": 81,
      "h": 29
    },
    {
      "frame": 313,
      "t": 5.22,
      "cx": 350,
      "cy": 607,
      "w": 81,
      "h": 29
    },
    {
      "frame": 314,
      "t": 5.23,
      "cx": 350,
      "cy": 607,
      "w": 81,
      "h": 29
    },
    {
      "frame": 315,
      "t": 5.25,
      "cx": 350,
      "cy": 607,
      "w": 81,
      "h": 29
    },
    {
      "frame": 316,
      "t": 5.27,
      "cx": 351,
      "cy": 607,
      "w": 82,
      "h": 29
    },
    {
      "frame": 317,
      "t": 5.28,
      "cx": 351,
      "cy": 607,
      "w": 82,
      "h": 29
    },
    {
      "frame": 318,
      "t": 5.3,
      "cx": 351,
      "cy": 607,
      "w": 82,
      "h": 29
    },
    {
      "frame": 319,
      "t": 5.32,
      "cx": 351,
      "cy": 607,
      "w": 82,
      "h": 29
    },
    {
      "frame": 320,
      "t": 5.33,
      "cx": 351,
      "cy": 607,
      "w": 82,
      "h": 29
    },
    {
      "frame": 321,
      "t": 5.35,
      "cx": 350,
      "cy": 607,
      "w": 81,
      "h": 29
    },
    {
      "frame": 322,
      "t": 5.37,
      "cx": 351,
      "cy": 607,
      "w": 82,
      "h": 29
    },
    {
      "frame": 323,
      "t": 5.38,
      "cx": 351,
      "cy": 607,
      "w": 82,
      "h": 29
    },
    {
      "frame": 324,
      "t": 5.4,
      "cx": 351,
      "cy": 607,
      "w": 82,
      "h": 29
    },
    {
      "frame": 325,
      "t": 5.42,
      "cx": 351,
      "cy": 607,
      "w": 82,
      "h": 29
    },
    {
      "frame": 326,
      "t": 5.43,
      "cx": 351,
      "cy": 608,
      "w": 83,
      "h": 28
    },
    {
      "frame": 327,
      "t": 5.45,
      "cx": 352,
      "cy": 608,
      "w": 84,
      "h": 28
    },
    {
      "frame": 328,
      "t": 5.47,
      "cx": 352,
      "cy": 608,
      "w": 85,
      "h": 28
    },
    {
      "frame": 329,
      "t": 5.48,
      "cx": 353,
      "cy": 608,
      "w": 86,
      "h": 28
    },
    {
      "frame": 330,
      "t": 5.5,
      "cx": 354,
      "cy": 608,
      "w": 88,
      "h": 28
    },
    {
      "frame": 331,
      "t": 5.52,
      "cx": 355,
      "cy": 608,
      "w": 84,
      "h": 28
    },
    {
      "frame": 332,
      "t": 5.53,
      "cx": 355,
      "cy": 608,
      "w": 84,
      "h": 28
    },
    {
      "frame": 333,
      "t": 5.55,
      "cx": 356,
      "cy": 608,
      "w": 86,
      "h": 28
    },
    {
      "frame": 334,
      "t": 5.57,
      "cx": 355,
      "cy": 608,
      "w": 83,
      "h": 28
    },
    {
      "frame": 335,
      "t": 5.58,
      "cx": 357,
      "cy": 607,
      "w": 81,
      "h": 27
    },
    {
      "frame": 336,
      "t": 5.6,
      "cx": 354,
      "cy": 607,
      "w": 77,
      "h": 27
    },
    {
      "frame": 337,
      "t": 5.62,
      "cx": 353,
      "cy": 608,
      "w": 71,
      "h": 26
    },
    {
      "frame": 338,
      "t": 5.63,
      "cx": 358,
      "cy": 607,
      "w": 76,
      "h": 27
    },
    {
      "frame": 339,
      "t": 5.65,
      "cx": 360,
      "cy": 607,
      "w": 78,
      "h": 27
    },
    {
      "frame": 340,
      "t": 5.67,
      "cx": 361,
      "cy": 607,
      "w": 79,
      "h": 27
    },
    {
      "frame": 341,
      "t": 5.68,
      "cx": 363,
      "cy": 607,
      "w": 78,
      "h": 27
    },
    {
      "frame": 342,
      "t": 5.7,
      "cx": 364,
      "cy": 608,
      "w": 76,
      "h": 28
    },
    {
      "frame": 343,
      "t": 5.72,
      "cx": 364,
      "cy": 607,
      "w": 75,
      "h": 28
    },
    {
      "frame": 344,
      "t": 5.73,
      "cx": 365,
      "cy": 607,
      "w": 72,
      "h": 30
    },
    {
      "frame": 345,
      "t": 5.75,
      "cx": 366,
      "cy": 607,
      "w": 71,
      "h": 30
    },
    {
      "frame": 346,
      "t": 5.77,
      "cx": 366,
      "cy": 607,
      "w": 70,
      "h": 30
    },
    {
      "frame": 347,
      "t": 5.78,
      "cx": 367,
      "cy": 606,
      "w": 70,
      "h": 31
    },
    {
      "frame": 348,
      "t": 5.8,
      "cx": 367,
      "cy": 606,
      "w": 69,
      "h": 29
    },
    {
      "frame": 349,
      "t": 5.82,
      "cx": 367,
      "cy": 606,
      "w": 69,
      "h": 29
    },
    {
      "frame": 350,
      "t": 5.83,
      "cx": 368,
      "cy": 607,
      "w": 70,
      "h": 28
    },
    {
      "frame": 351,
      "t": 5.85,
      "cx": 368,
      "cy": 608,
      "w": 70,
      "h": 28
    },
    {
      "frame": 352,
      "t": 5.87,
      "cx": 368,
      "cy": 607,
      "w": 70,
      "h": 30
    },
    {
      "frame": 353,
      "t": 5.88,
      "cx": 368,
      "cy": 606,
      "w": 69,
      "h": 31
    },
    {
      "frame": 354,
      "t": 5.9,
      "cx": 369,
      "cy": 606,
      "w": 70,
      "h": 31
    },
    {
      "frame": 355,
      "t": 5.92,
      "cx": 369,
      "cy": 606,
      "w": 70,
      "h": 30
    },
    {
      "frame": 356,
      "t": 5.93,
      "cx": 369,
      "cy": 606,
      "w": 69,
      "h": 29
    },
    {
      "frame": 357,
      "t": 5.95,
      "cx": 369,
      "cy": 606,
      "w": 71,
      "h": 30
    },
    {
      "frame": 358,
      "t": 5.97,
      "cx": 370,
      "cy": 604,
      "w": 73,
      "h": 33
    },
    {
      "frame": 359,
      "t": 5.98,
      "cx": 370,
      "cy": 604,
      "w": 73,
      "h": 32
    },
    {
      "frame": 360,
      "t": 6.0,
      "cx": 370,
      "cy": 603,
      "w": 73,
      "h": 33
    },
    {
      "frame": 361,
      "t": 6.02,
      "cx": 370,
      "cy": 603,
      "w": 73,
      "h": 33
    },
    {
      "frame": 363,
      "t": 6.05,
      "cx": 792,
      "cy": 227,
      "w": 68,
      "h": 29
    },
    {
      "frame": 364,
      "t": 6.07,
      "cx": 788,
      "cy": 228,
      "w": 67,
      "h": 28
    },
    {
      "frame": 365,
      "t": 6.08,
      "cx": 785,
      "cy": 229,
      "w": 64,
      "h": 28
    },
    {
      "frame": 366,
      "t": 6.1,
      "cx": 782,
      "cy": 228,
      "w": 67,
      "h": 30
    },
    {
      "frame": 367,
      "t": 6.12,
      "cx": 779,
      "cy": 228,
      "w": 69,
      "h": 30
    },
    {
      "frame": 368,
      "t": 6.13,
      "cx": 775,
      "cy": 227,
      "w": 71,
      "h": 31
    },
    {
      "frame": 369,
      "t": 6.15,
      "cx": 772,
      "cy": 228,
      "w": 68,
      "h": 34
    },
    {
      "frame": 370,
      "t": 6.17,
      "cx": 767,
      "cy": 226,
      "w": 67,
      "h": 35
    },
    {
      "frame": 371,
      "t": 6.18,
      "cx": 765,
      "cy": 228,
      "w": 68,
      "h": 32
    },
    {
      "frame": 372,
      "t": 6.2,
      "cx": 763,
      "cy": 229,
      "w": 68,
      "h": 31
    },
    {
      "frame": 373,
      "t": 6.22,
      "cx": 759,
      "cy": 230,
      "w": 69,
      "h": 31
    },
    {
      "frame": 380,
      "t": 6.33,
      "cx": 753,
      "cy": 232,
      "w": 37,
      "h": 29
    },
    {
      "frame": 381,
      "t": 6.35,
      "cx": 747,
      "cy": 233,
      "w": 42,
      "h": 27
    },
    {
      "frame": 744,
      "t": 12.4,
      "cx": 921,
      "cy": 614,
      "w": 99,
      "h": 21
    },
    {
      "frame": 745,
      "t": 12.42,
      "cx": 921,
      "cy": 612,
      "w": 101,
      "h": 23
    },
    {
      "frame": 746,
      "t": 12.43,
      "cx": 922,
      "cy": 614,
      "w": 98,
      "h": 21
    },
    {
      "frame": 747,
      "t": 12.45,
      "cx": 920,
      "cy": 611,
      "w": 101,
      "h": 25
    },
    {
      "frame": 748,
      "t": 12.47,
      "cx": 920,
      "cy": 611,
      "w": 102,
      "h": 25
    },
    {
      "frame": 749,
      "t": 12.48,
      "cx": 919,
      "cy": 610,
      "w": 104,
      "h": 26
    },
    {
      "frame": 750,
      "t": 12.5,
      "cx": 919,
      "cy": 609,
      "w": 104,
      "h": 27
    },
    {
      "frame": 751,
      "t": 12.52,
      "cx": 920,
      "cy": 614,
      "w": 102,
      "h": 22
    },
    {
      "frame": 752,
      "t": 12.53,
      "cx": 920,
      "cy": 614,
      "w": 101,
      "h": 22
    },
    {
      "frame": 753,
      "t": 12.55,
      "cx": 921,
      "cy": 614,
      "w": 100,
      "h": 21
    },
    {
      "frame": 754,
      "t": 12.57,
      "cx": 921,
      "cy": 614,
      "w": 100,
      "h": 21
    },
    {
      "frame": 755,
      "t": 12.58,
      "cx": 921,
      "cy": 614,
      "w": 100,
      "h": 22
    },
    {
      "frame": 756,
      "t": 12.6,
      "cx": 921,
      "cy": 614,
      "w": 100,
      "h": 22
    },
    {
      "frame": 757,
      "t": 12.62,
      "cx": 920,
      "cy": 614,
      "w": 99,
      "h": 22
    },
    {
      "frame": 758,
      "t": 12.63,
      "cx": 920,
      "cy": 614,
      "w": 99,
      "h": 22
    },
    {
      "frame": 759,
      "t": 12.65,
      "cx": 921,
      "cy": 614,
      "w": 98,
      "h": 21
    },
    {
      "frame": 760,
      "t": 12.67,
      "cx": 921,
      "cy": 614,
      "w": 98,
      "h": 21
    },
    {
      "frame": 761,
      "t": 12.68,
      "cx": 921,
      "cy": 614,
      "w": 97,
      "h": 21
    },
    {
      "frame": 762,
      "t": 12.7,
      "cx": 922,
      "cy": 614,
      "w": 95,
      "h": 21
    },
    {
      "frame": 763,
      "t": 12.72,
      "cx": 922,
      "cy": 614,
      "w": 96,
      "h": 21
    },
    {
      "frame": 764,
      "t": 12.73,
      "cx": 923,
      "cy": 614,
      "w": 94,
      "h": 21
    },
    {
      "frame": 765,
      "t": 12.75,
      "cx": 923,
      "cy": 614,
      "w": 94,
      "h": 21
    },
    {
      "frame": 766,
      "t": 12.77,
      "cx": 925,
      "cy": 614,
      "w": 92,
      "h": 21
    },
    {
      "frame": 767,
      "t": 12.78,
      "cx": 925,
      "cy": 614,
      "w": 92,
      "h": 21
    },
    {
      "frame": 768,
      "t": 12.8,
      "cx": 925,
      "cy": 614,
      "w": 89,
      "h": 21
    },
    {
      "frame": 769,
      "t": 12.82,
      "cx": 926,
      "cy": 614,
      "w": 87,
      "h": 21
    },
    {
      "frame": 770,
      "t": 12.83,
      "cx": 926,
      "cy": 614,
      "w": 87,
      "h": 21
    },
    {
      "frame": 771,
      "t": 12.85,
      "cx": 927,
      "cy": 614,
      "w": 85,
      "h": 21
    },
    {
      "frame": 772,
      "t": 12.87,
      "cx": 927,
      "cy": 614,
      "w": 88,
      "h": 21
    },
    {
      "frame": 773,
      "t": 12.88,
      "cx": 926,
      "cy": 614,
      "w": 90,
      "h": 21
    },
    {
      "frame": 774,
      "t": 12.9,
      "cx": 926,
      "cy": 614,
      "w": 90,
      "h": 21
    },
    {
      "frame": 778,
      "t": 12.97,
      "cx": 924,
      "cy": 614,
      "w": 97,
      "h": 22
    },
    {
      "frame": 779,
      "t": 12.98,
      "cx": 925,
      "cy": 613,
      "w": 96,
      "h": 22
    },
    {
      "frame": 780,
      "t": 13.0,
      "cx": 924,
      "cy": 612,
      "w": 97,
      "h": 23
    },
    {
      "frame": 1136,
      "t": 18.93,
      "cx": 709,
      "cy": 250,
      "w": 81,
      "h": 29
    },
    {
      "frame": 1137,
      "t": 18.95,
      "cx": 712,
      "cy": 249,
      "w": 82,
      "h": 31
    },
    {
      "frame": 1138,
      "t": 18.97,
      "cx": 714,
      "cy": 249,
      "w": 77,
      "h": 31
    },
    {
      "frame": 1139,
      "t": 18.98,
      "cx": 717,
      "cy": 249,
      "w": 75,
      "h": 34
    },
    {
      "frame": 1143,
      "t": 19.05,
      "cx": 729,
      "cy": 253,
      "w": 73,
      "h": 31
    },
    {
      "frame": 1144,
      "t": 19.07,
      "cx": 732,
      "cy": 253,
      "w": 73,
      "h": 31
    },
    {
      "frame": 1149,
      "t": 19.15,
      "cx": 748,
      "cy": 250,
      "w": 69,
      "h": 29
    },
    {
      "frame": 1159,
      "t": 19.32,
      "cx": 782,
      "cy": 253,
      "w": 95,
      "h": 31
    },
    {
      "frame": 1160,
      "t": 19.33,
      "cx": 780,
      "cy": 253,
      "w": 89,
      "h": 33
    },
    {
      "frame": 1161,
      "t": 19.35,
      "cx": 777,
      "cy": 252,
      "w": 87,
      "h": 33
    },
    {
      "frame": 1162,
      "t": 19.37,
      "cx": 778,
      "cy": 254,
      "w": 82,
      "h": 32
    },
    {
      "frame": 1163,
      "t": 19.38,
      "cx": 781,
      "cy": 253,
      "w": 88,
      "h": 32
    },
    {
      "frame": 1164,
      "t": 19.4,
      "cx": 783,
      "cy": 252,
      "w": 91,
      "h": 34
    },
    {
      "frame": 1165,
      "t": 19.42,
      "cx": 780,
      "cy": 252,
      "w": 81,
      "h": 34
    },
    {
      "frame": 1166,
      "t": 19.43,
      "cx": 775,
      "cy": 251,
      "w": 69,
      "h": 35
    },
    {
      "frame": 1167,
      "t": 19.45,
      "cx": 777,
      "cy": 251,
      "w": 71,
      "h": 35
    },
    {
      "frame": 1168,
      "t": 19.47,
      "cx": 783,
      "cy": 252,
      "w": 80,
      "h": 36
    }
  ]
}